{
  "mp": {
    "name": "Mechanical Prosthesis",
    "image": "https://cdn.discordapp.com/emojis/1110369514165653594.png",
    "description": "An insane mechanical arm", 
    "usage": "Increases 20% DMG given."
  },
  
  "mots": {
    "name": "Manifestation of the Soul",
    "image": "https://cdn.discordapp.com/emojis/1110360979834929152.png",
    "description": "jojo reference wotefok", 
    "usage": "After using this item, will be granted a completely random ability for one turn."
  },
  
  "dp": {
    "name": "Disposable Shield",
    "image": "https://cdn.discordapp.com/emojis/1110369384121241692.png",
    "description": "shield aaa", 
    "usage": "Reduces 30% DMG taken. \n Breaks if it takes critical DMG."
  }
}
